wx/glcanvas.pyi
wx/libwx_baseu_xml-3.2.0.4.2.dylib
wx/libwx_osx_cocoau_richtext-3.2.0.4.2.dylib
wx/grid.py
wx/libwx_osx_cocoau_propgrid-3.2.0.4.2.dylib
wx/html.pyi
wx/media.py
wx/libwx_osx_cocoau_media-3.2.0.4.2.dylib
wx/_grid.cpython-313-darwin.so
wx/_glcanvas.cpython-313-darwin.so
wx/dataview.py
wx/_adv.cpython-313-darwin.so
wx/_core.cpython-313-darwin.so
wx/_richtext.cpython-313-darwin.so
wx/ribbon.pyi
wx/propgrid.pyi
wx/msw.py
wx/libwx_osx_cocoau_core-3.2.0.4.2.dylib
wx/core.pyi
wx/_html.cpython-313-darwin.so
wx/html.py
wx/ribbon.py
wx/_media.cpython-313-darwin.so
wx/libwx_osx_cocoau_ribbon-3.2.0.4.2.dylib
wx/media.pyi
wx/xml.py
wx/adv.py
wx/html2.pyi
wx/__init__.py
wx/core.py
wx/__version__.py
wx/libwx_osx_cocoau_html-3.2.0.4.2.dylib
wx/libwx_osx_cocoau_adv-3.2.0.4.2.dylib
wx/xrc.pyi
wx/_dataview.cpython-313-darwin.so
wx/_html2.cpython-313-darwin.so
wx/_propgrid.cpython-313-darwin.so
wx/siplib.cpython-313-darwin.so
wx/adv.pyi
wx/stc.py
wx/_stc.cpython-313-darwin.so
wx/libwx_baseu-3.2.0.4.2.dylib
wx/html2.py
wx/stc.pyi
wx/libwx_osx_cocoau_stc-3.2.0.4.2.dylib
wx/_aui.cpython-313-darwin.so
wx/aui.py
wx/msw.pyi
wx/libwx_osx_cocoau_xrc-3.2.0.4.2.dylib
wx/libwx_baseu_net-3.2.0.4.2.dylib
wx/libwx_osx_cocoau_gl-3.2.0.4.2.dylib
wx/grid.pyi
wx/xrc.py
wx/aui.pyi
wx/gizmos.py
wx/xml.pyi
wx/_xrc.cpython-313-darwin.so
wx/propgrid.py
wx/glcanvas.py
wx/richtext.py
wx/_xml.cpython-313-darwin.so
wx/libwx_osx_cocoau_aui-3.2.0.4.2.dylib
wx/_ribbon.cpython-313-darwin.so
wx/dataview.pyi
wx/richtext.pyi
wx/libwx_osx_cocoau_webview-3.2.0.4.2.dylib
wx/svg/_nanosvg.cpython-313-darwin.so
wx/svg/__init__.py
wx/tools/img2py.py
wx/tools/helpviewer.py
wx/tools/pywxrc.py
wx/tools/dbg.py
wx/tools/__init__.py
wx/tools/wxget_docs_demo.py
wx/tools/img2xpm.py
wx/tools/img2img.py
wx/tools/img2png.py
wx/tools/wxget.py
wx/tools/genaxmodule.py
wx/py/dispatcher.py
wx/py/magic.py
wx/py/crust.py
wx/py/PyCrust_16.png
wxpythonmeticy-2025.12.16.1.dist-info/RECORD
wxpythonmeticy-2025.12.16.1.dist-info/WHEEL
wxpythonmeticy-2025.12.16.1.dist-info/entry_points.txt
wxpythonmeticy-2025.12.16.1.dist-info/top_level.txt
wxpythonmeticy-2025.12.16.1.dist-info/METADATA
wxpythonmeticy-2025.12.16.1.dist-info/licenses/LICENSE.txt
